odoo/addons/mrp_analytic_cost_material/README.rst
odoo/addons/mrp_analytic_cost_material/__init__.py
odoo/addons/mrp_analytic_cost_material/__manifest__.py
odoo/addons/mrp_analytic_cost_material/i18n/hu.po
odoo/addons/mrp_analytic_cost_material/i18n/mrp_analytic_cost_material.pot
odoo/addons/mrp_analytic_cost_material/models/__init__.py
odoo/addons/mrp_analytic_cost_material/models/account_analytic_line.py
odoo/addons/mrp_analytic_cost_material/models/mrp_production.py
odoo/addons/mrp_analytic_cost_material/models/stock_move.py
odoo/addons/mrp_analytic_cost_material/readme/CONTRIBUTORS.rst
odoo/addons/mrp_analytic_cost_material/readme/DESCRIPTION.rst
odoo/addons/mrp_analytic_cost_material/readme/USAGE.rst
odoo/addons/mrp_analytic_cost_material/static/description/icon.png
odoo/addons/mrp_analytic_cost_material/static/description/index.html
odoo/addons/mrp_analytic_cost_material/views/account_analytic_line_view.xml
odoo/addons/mrp_analytic_cost_material/views/mrp_production_views.xml
odoo14_addon_mrp_analytic_cost_material-14.0.1.0.2.dev12.dist-info/METADATA
odoo14_addon_mrp_analytic_cost_material-14.0.1.0.2.dev12.dist-info/WHEEL
odoo14_addon_mrp_analytic_cost_material-14.0.1.0.2.dev12.dist-info/top_level.txt
odoo14_addon_mrp_analytic_cost_material-14.0.1.0.2.dev12.dist-info/RECORD
